AUTHORS.rst
CONTRIBUTING.rst
HISTORY.rst
LICENSE
MANIFEST.in
README.rst
setup.cfg
setup.py
django_usersettings2.egg-info/PKG-INFO
django_usersettings2.egg-info/SOURCES.txt
django_usersettings2.egg-info/dependency_links.txt
django_usersettings2.egg-info/not-zip-safe
django_usersettings2.egg-info/requires.txt
django_usersettings2.egg-info/top_level.txt
usersettings/__init__.py
usersettings/admin.py
usersettings/apps.py
usersettings/context_processors.py
usersettings/middleware.py
usersettings/models.py
usersettings/shortcuts.py
usersettings/static/css/usersettings.css
usersettings/static/js/usersettings.js
usersettings/templates/admin/usersettings/select_site_form.html