Metadata-Version: 1.1
Name: django-usersettings2
Version: 0.1.6
Summary: The missing extension to the Django “sites” framework, use it to store additional information for your Django-powered sites.
Home-page: https://github.com/mishbahr/django-usersettings2
Author: Mishbah Razzaque
Author-email: mishbahx@gmail.com
License: BSD
Keywords: django-usersettings2
Platform: UNKNOWN
Classifier: Development Status :: 4 - Beta
Classifier: Framework :: Django
Classifier: Intended Audience :: Developers
Classifier: License :: OSI Approved :: BSD License
Classifier: Natural Language :: English
Classifier: Programming Language :: Python :: 2
Classifier: Programming Language :: Python :: 2.6
Classifier: Programming Language :: Python :: 2.7
Classifier: Programming Language :: Python :: 3
Classifier: Programming Language :: Python :: 3.3
